bl101
