Metadata-Version: 2.1
Name: bl101
Version: 2.7
Summary: Blockchain 101 Course
Home-page: http://github.com/unpackAI/BL101
Author: Dirk
Author-email: dirk.kalmbach@gmail.com
License: MIT
Platform: UNKNOWN
